sparsekmeans/__init__.py
sparsekmeans/sparse_kmeans.py
sparsekmeans-0.2.1.dist-info/LICENSE
sparsekmeans-0.2.1.dist-info/METADATA
sparsekmeans-0.2.1.dist-info/WHEEL
sparsekmeans-0.2.1.dist-info/top_level.txt
sparsekmeans-0.2.1.dist-info/RECORD
